commonutil_net_thrift/__init__.py
commonutil_net_thrift/py.typed
commonutil_net_thrift/client/__init__.py
commonutil_net_thrift/client/roundrobin.py
commonutil_net_thrift/client/types.py
commonutil_net_thrift/connector/__init__.py
commonutil_net_thrift/connector/binarysocket.py
commonutil_net_thrift/connector/exceptions.py
commonutil_net_thrift-3.1.0.dist-info/METADATA
commonutil_net_thrift-3.1.0.dist-info/WHEEL
commonutil_net_thrift-3.1.0.dist-info/top_level.txt
commonutil_net_thrift-3.1.0.dist-info/RECORD
